save_to_zotero/__init__.py
save_to_zotero/__main__.py
save_to_zotero/save_to_zotero.py
save_to_zotero/utils/__init__.py
save_to_zotero/utils/misc.py
save_to_zotero/utils/webpage.py
save_to_zotero-1.2.1.dist-info/licenses/LICENSE
save_to_zotero-1.2.1.dist-info/METADATA
save_to_zotero-1.2.1.dist-info/WHEEL
save_to_zotero-1.2.1.dist-info/entry_points.txt
save_to_zotero-1.2.1.dist-info/top_level.txt
save_to_zotero-1.2.1.dist-info/RECORD
