Metadata-Version: 2.4
Name: save_to_zotero
Version: 1.2.1
Summary: Save webpages as PDFs and add them to Zotero
Home-page: https://github.com/thiswillbeyourgithub/save_to_zotero
Author: save_to_zotero
Keywords: zotero,research,publication,journal,paper,upload,pdf,document,archive,omnivore,hoarder,highlight,annotation
Classifier: Development Status :: 4 - Beta
Classifier: Intended Audience :: Science/Research
Classifier: Programming Language :: Python :: 3
Classifier: Programming Language :: Python :: 3.7
Classifier: Programming Language :: Python :: 3.8
Classifier: Programming Language :: Python :: 3.9
Classifier: Programming Language :: Python :: 3.10
Requires-Python: >=3.7
License-File: LICENSE
Requires-Dist: fire>=0.7.0
Requires-Dist: pyzotero>=1.6.11
Requires-Dist: playwright>=1.51.0
Requires-Dist: requests>=2.32.3
Requires-Dist: loguru>=0.7.3
Requires-Dist: platformdirs>=4.3.7
Dynamic: author
Dynamic: classifier
Dynamic: description
Dynamic: description-content-type
Dynamic: home-page
Dynamic: keywords
Dynamic: license-file
Dynamic: requires-dist
Dynamic: requires-python
Dynamic: summary
